Metadata-Version: 1.2
Name: usb-descriptors
Version: 0.0
Summary: python library providing utilities, data structures, constants, parsers, and tools for working with USB data
Home-page: https://github.com/hansfbaier/python-usb-descriptors
Author: Hans Baier
Author-email: hansfbaier@gmail.com
License: BSD
Platform: any
Classifier: Programming Language :: Python
Classifier: Development Status :: 1 - Planning
Classifier: Natural Language :: English
Classifier: Environment :: Console
Classifier: Environment :: Plugins
Classifier: Intended Audience :: Developers
Classifier: Intended Audience :: Science/Research
Classifier: License :: OSI Approved :: BSD License
Classifier: Operating System :: OS Independent
Classifier: Topic :: Scientific/Engineering
Classifier: Topic :: Security
Requires-Python: ~=3.7
